swmonkey/__init__.py
swmonkey/main.cpython-310-x86_64-linux-gnu.so
swmonkey/main.py
swmonkey/runner.cpython-310-x86_64-linux-gnu.so
swmonkey/runner.py
test_module/__init__.py
swmonkey-0.41.dist-info/METADATA
swmonkey-0.41.dist-info/WHEEL
swmonkey-0.41.dist-info/entry_points.txt
swmonkey-0.41.dist-info/top_level.txt
swmonkey-0.41.dist-info/RECORD
