Metadata-Version: 2.1
Name: swmonkey
Version: 0.41
Summary: A tool for monkey test on Linux GUI
Author: Li Saifei
Author-email: waltermitty121906@gmail.com
Requires-Dist: pyautogui
Requires-Dist: psutil
Requires-Dist: pywinctl
